pebble_tool/__init__.py
pebble_tool/account.py
pebble_tool/exceptions.py
pebble_tool/commands/__init__.py
pebble_tool/commands/account.py
pebble_tool/commands/base.py
pebble_tool/commands/data_logging.py
pebble_tool/commands/emucontrol.py
pebble_tool/commands/install.py
pebble_tool/commands/logs.py
pebble_tool/commands/ping.py
pebble_tool/commands/repl.py
pebble_tool/commands/screenshot.py
pebble_tool/commands/timeline.py
pebble_tool/commands/transcription_server.py
pebble_tool/commands/sdk/__init__.py
pebble_tool/commands/sdk/create.py
pebble_tool/commands/sdk/emulator.py
pebble_tool/commands/sdk/manage.py
pebble_tool/commands/sdk/project/__init__.py
pebble_tool/commands/sdk/project/analyse_size.py
pebble_tool/commands/sdk/project/build.py
pebble_tool/commands/sdk/project/convert.py
pebble_tool/commands/sdk/project/debug.py
pebble_tool/commands/sdk/project/package.py
pebble_tool/sdk/__init__.py
pebble_tool/sdk/cloudpebble.py
pebble_tool/sdk/emulator.py
pebble_tool/sdk/manager.py
pebble_tool/sdk/project.py
pebble_tool/sdk/requirements.py
pebble_tool/sdk/templates/templates.json
pebble_tool/sdk/templates/app/ai.md
pebble_tool/sdk/templates/app/index.js
pebble_tool/sdk/templates/app/main.c
pebble_tool/sdk/templates/app/package.json
pebble_tool/sdk/templates/app/simple.c
pebble_tool/sdk/templates/app/worker.c
pebble_tool/sdk/templates/app/wscript
pebble_tool/sdk/templates/common/gitignore
pebble_tool/sdk/templates/lib/lib.c
pebble_tool/sdk/templates/lib/lib.h
pebble_tool/sdk/templates/lib/lib.js
pebble_tool/sdk/templates/lib/package.json
pebble_tool/sdk/templates/lib/wscript
pebble_tool/sdk/templates/moddable/index.js
pebble_tool/sdk/templates/moddable/main.js
pebble_tool/sdk/templates/moddable/manifest.json
pebble_tool/sdk/templates/moddable/mdbl.c
pebble_tool/sdk/templates/moddable/package.json
pebble_tool/sdk/templates/moddable/wscript
pebble_tool/sdk/templates/rocky/app.js
pebble_tool/sdk/templates/rocky/index.js
pebble_tool/sdk/templates/rocky/package.json
pebble_tool-5.0.22.dist-info/METADATA
pebble_tool-5.0.22.dist-info/WHEEL
pebble_tool-5.0.22.dist-info/entry_points.txt
pebble_tool-5.0.22.dist-info/licenses/LICENSE
pebble_tool-5.0.22.dist-info/RECORD
