Metadata-Version: 2.4
Name: pebble-tool
Version: 5.0.22
Summary: Tool for interacting with pebbles.
Project-URL: Homepage, https://github.com/coredevices/pebble-tool
Author-email: Core Devices LLC <griffin@griffinli.com>
License-Expression: MIT
License-File: LICENSE
Requires-Python: <3.14,>3.9
Requires-Dist: cobs>=1.2.0
Requires-Dist: colorama>=0.3.3
Requires-Dist: freetype-py>=2.5.1
Requires-Dist: httplib2>=0.19.0
Requires-Dist: libpebble2>=0.0.30
Requires-Dist: oauth2client>=4.1.3
Requires-Dist: packaging>=25.0
Requires-Dist: progressbar2>=2.7.3
Requires-Dist: pyasn1-modules>=0.0.6
Requires-Dist: pyasn1>=0.1.8
Requires-Dist: pypkjs>=2.0.0
Requires-Dist: pypng>=0.20220715.0
Requires-Dist: pyqrcode>=1.1
Requires-Dist: pyserial>=3.5
Requires-Dist: requests>=2.32.4
Requires-Dist: rsa>=4.9.1
Requires-Dist: six>=1.17.0
Requires-Dist: sourcemap>=0.2.0
Requires-Dist: websocket-client>=1.8.0
Requires-Dist: websockify>=0.13.0
Requires-Dist: wheel>=0.45.1
